{"SPY": {"price": 750.46, "daily": -0.02, "returns": {"1M": 4.93, "3M": 8.56, "6M": 14.52, "1Y": 31.07, "3Y": 86.29}, "updated": "2026-05-27"}, "IVV": {"price": 754.17, "daily": 0.02, "returns": {"1M": 4.96, "3M": 8.61, "6M": 14.58, "1Y": 31.19, "3Y": 86.83}, "updated": "2026-05-27"}, "VOO": {"price": 689.96, "daily": -0.01, "returns": {"1M": 4.94, "3M": 8.57, "6M": 14.55, "1Y": 31.15, "3Y": 86.79}, "updated": "2026-05-27"}, "VTI": {"price": 369.36, "daily": -0.03, "returns": {"1M": 4.77, "3M": 8.39, "6M": 14.75, "1Y": 31.11, "3Y": 85.16}, "updated": "2026-05-27"}, "ITOT": {"price": 164.05, "daily": -0.04, "returns": {"1M": 4.79, "3M": 8.5, "6M": 14.91, "1Y": 31.14, "3Y": 85.26}, "updated": "2026-05-27"}, "SCHB": {"price": 28.94, "daily": 0.03, "returns": {"1M": 4.82, "3M": 8.52, "6M": 14.92, "1Y": 31.13, "3Y": 85.36}, "updated": "2026-05-27"}, "IWM": {"price": 290.37, "daily": -0.05, "returns": {"1M": 4.77, "3M": 9.94, "6M": 23.88, "1Y": 44.89, "3Y": 70.88}, "updated": "2026-05-27"}, "IWF": {"price": 125.71, "daily": 0.04, "returns": {"1M": 4.77, "3M": 9.77, "6M": 10.09, "1Y": 29.22, "3Y": 100.45}, "updated": "2026-05-27"}, "IWD": {"price": 237.93, "daily": -0.16, "returns": {"1M": 4.51, "3M": 6.13, "6M": 18.2, "1Y": 29.99, "3Y": 66.11}, "updated": "2026-05-27"}, "MDY": {"price": 678.56, "daily": -0.37, "returns": {"1M": 2.07, "3M": 3.75, "6M": 17.24, "1Y": 26.09, "3Y": 56.86}, "updated": "2026-05-27"}, "IJH": {"price": 74.36, "daily": -0.39, "returns": {"1M": 2.09, "3M": 3.84, "6M": 17.48, "1Y": 26.5, "3Y": 58.19}, "updated": "2026-05-27"}, "IJR": {"price": 139.62, "daily": 0.02, "returns": {"1M": 2.24, "3M": 7.03, "6M": 21.55, "1Y": 36.1, "3Y": 55.95}, "updated": "2026-05-27"}, "QQQ": {"price": 729.45, "daily": -0.11, "returns": {"1M": 9.82, "3M": 18.44, "6M": 23.94, "1Y": 43.94, "3Y": 120.61}, "updated": "2026-05-27"}, "QQQM": {"price": 300.38, "daily": -0.1, "returns": {"1M": 9.82, "3M": 18.5, "6M": 23.98, "1Y": 44.03, "3Y": 121.18}, "updated": "2026-05-27"}, "VUG": {"price": 88.21, "daily": 0.01, "returns": {"1M": 5.65, "3M": 12.66, "6M": 12.87, "1Y": 31.45, "3Y": 106.14}, "updated": "2026-05-27"}, "VONG": {"price": 129.43, "daily": 0.09, "returns": {"1M": 4.78, "3M": 9.86, "6M": 10.2, "1Y": 29.36, "3Y": 101.15}, "updated": "2026-05-27"}, "IWY": {"price": 294.85, "daily": 0.03, "returns": {"1M": 4.94, "3M": 10.27, "6M": 10.39, "1Y": 30.21, "3Y": 104.74}, "updated": "2026-05-27"}, "VEA": {"price": 71.41, "daily": -0.52, "returns": {"1M": 4.91, "3M": 1.81, "6M": 21.7, "1Y": 33.88, "3Y": 69.66}, "updated": "2026-05-27"}, "VWO": {"price": 60.29, "daily": 0.1, "returns": {"1M": 2.66, "3M": 2.17, "6M": 15.84, "1Y": 29.65, "3Y": 66.2}, "updated": "2026-05-27"}, "EFA": {"price": 104.77, "daily": -0.34, "returns": {"1M": 3.34, "3M": -0.84, "6M": 15.13, "1Y": 23.26, "3Y": 56.66}, "updated": "2026-05-27"}, "EEM": {"price": 68.39, "daily": -0.01, "returns": {"1M": 7.46, "3M": 8.02, "6M": 30.64, "1Y": 51.5, "3Y": 88.93}, "updated": "2026-05-27"}, "IEFA": {"price": 97.94, "daily": -0.39, "returns": {"1M": 3.47, "3M": -0.63, "6M": 15.6, "1Y": 24.11, "3Y": 57.77}, "updated": "2026-05-27"}, "IEMG": {"price": 83.46, "daily": -0.13, "returns": {"1M": 6.97, "3M": 7.59, "6M": 29.47, "1Y": 49.61, "3Y": 88.58}, "updated": "2026-05-27"}, "VGK": {"price": 89.32, "daily": -0.18, "returns": {"1M": 3.2, "3M": -0.83, "6M": 14.54, "1Y": 21.03, "3Y": 56.58}, "updated": "2026-05-27"}, "EWJ": {"price": 92.29, "daily": -0.66, "returns": {"1M": 5.26, "3M": -0.16, "6M": 17.92, "1Y": 32.16, "3Y": 65.4}, "updated": "2026-05-27"}, "FXI": {"price": 35.32, "daily": -1.2, "returns": {"1M": -3.1, "3M": -8.07, "6M": -7.79, "1Y": 0.66, "3Y": 36.29}, "updated": "2026-05-27"}, "EWZ": {"price": 36.11, "daily": -1.04, "returns": {"1M": -9.48, "3M": -8.79, "6M": 16.69, "1Y": 37.69, "3Y": 46.07}, "updated": "2026-05-27"}, "AGG": {"price": 98.8, "daily": 0.08, "returns": {"1M": -0.31, "3M": -1.25, "6M": 0.32, "1Y": 5.68, "3Y": 12.6}, "updated": "2026-05-27"}, "BND": {"price": 73.28, "daily": 0.1, "returns": {"1M": -0.3, "3M": -1.22, "6M": 0.28, "1Y": 5.56, "3Y": 12.57}, "updated": "2026-05-27"}, "TLT": {"price": 85.3, "daily": 0.24, "returns": {"1M": -0.77, "3M": -4.08, "6M": -2.55, "1Y": 5.47, "3Y": -4.62}, "updated": "2026-05-27"}, "IEF": {"price": 94.32, "daily": 0.04, "returns": {"1M": -0.74, "3M": -2.18, "6M": -1.09, "1Y": 4.5, "3Y": 7.51}, "updated": "2026-05-27"}, "SHY": {"price": 82.22, "daily": 0.01, "returns": {"1M": -0.11, "3M": -0.13, "6M": 0.8, "1Y": 3.42, "3Y": 12.3}, "updated": "2026-05-27"}, "LQD": {"price": 108.93, "daily": 0.14, "returns": {"1M": 0.06, "3M": -1.31, "6M": 0.47, "1Y": 7.21, "3Y": 16.63}, "updated": "2026-05-27"}, "HYG": {"price": 80.13, "daily": -0.06, "returns": {"1M": 0.05, "3M": 0.52, "6M": 2.66, "1Y": 7.59, "3Y": 28.98}, "updated": "2026-05-27"}, "MUB": {"price": 106.89, "daily": 0.23, "returns": {"1M": -0.21, "3M": -0.92, "6M": 1.36, "1Y": 6.37, "3Y": 10.68}, "updated": "2026-05-27"}, "VCIT": {"price": 82.6, "daily": 0.07, "returns": {"1M": -0.19, "3M": -1.2, "6M": 0.63, "1Y": 7.02, "3Y": 19.85}, "updated": "2026-05-27"}, "XLK": {"price": 184.43, "daily": -0.38, "returns": {"1M": 14.86, "3M": 29.12, "6M": 35.39, "1Y": 63.56, "3Y": 139.13}, "updated": "2026-05-27"}, "XLF": {"price": 51.42, "daily": -0.83, "returns": {"1M": -0.75, "3M": -0.36, "6M": 0.38, "1Y": 4.32, "3Y": 65.55}, "updated": "2026-05-27"}, "XLV": {"price": 148.79, "daily": 0.19, "returns": {"1M": 3.72, "3M": -5.34, "6M": -2.96, "1Y": 16.19, "3Y": 19.12}, "updated": "2026-05-27"}, "XLE": {"price": 56.99, "daily": -1.49, "returns": {"1M": 0.39, "3M": 4.54, "6M": 29.39, "1Y": 43.48, "3Y": 57.8}, "updated": "2026-05-27"}, "XLY": {"price": 121.55, "daily": 1.76, "returns": {"1M": 3.15, "3M": 4.02, "6M": 8.24, "1Y": 16.32, "3Y": 64.38}, "updated": "2026-05-27"}, "XLP": {"price": 84.58, "daily": 1.14, "returns": {"1M": 2.72, "3M": -4.44, "6M": 10.06, "1Y": 6.52, "3Y": 20.89}, "updated": "2026-05-27"}, "XLI": {"price": 174.3, "daily": 0.0, "returns": {"1M": 1.04, "3M": -0.46, "6M": 17.21, "1Y": 25.43, "3Y": 82.68}, "updated": "2026-05-27"}, "XLB": {"price": 51.18, "daily": 0.37, "returns": {"1M": -1.16, "3M": -3.11, "6M": 19.68, "1Y": 21.78, "3Y": 38.07}, "updated": "2026-05-27"}, "XLU": {"price": 45.14, "daily": -0.42, "returns": {"1M": -2.27, "3M": -4.02, "6M": 3.91, "1Y": 14.54, "3Y": 49.7}, "updated": "2026-05-27"}, "XLRE": {"price": 44.63, "daily": -0.18, "returns": {"1M": 2.62, "3M": 3.43, "6M": 11.05, "1Y": 13.64, "3Y": 36.66}, "updated": "2026-05-27"}, "XLC": {"price": 116.26, "daily": 0.61, "returns": {"1M": 0.39, "3M": 0.11, "6M": 4.57, "1Y": 17.48, "3Y": 95.63}, "updated": "2026-05-27"}, "GLD": {"price": 408.49, "daily": -1.33, "returns": {"1M": -4.98, "3M": -13.72, "6M": 9.14, "1Y": 31.88, "3Y": 122.44}, "updated": "2026-05-27"}, "SLV": {"price": 67.5, "daily": -3.18, "returns": {"1M": -1.21, "3M": -15.67, "6M": 49.01, "1Y": 121.67, "3Y": 208.78}, "updated": "2026-05-27"}, "GDX": {"price": 85.44, "daily": -3.46, "returns": {"1M": -7.72, "3M": -23.14, "6M": 16.85, "1Y": 70.32, "3Y": 175.19}, "updated": "2026-05-27"}, "USO": {"price": 131.03, "daily": -4.36, "returns": {"1M": -2.74, "3M": 64.34, "6M": 89.08, "1Y": 92.72, "3Y": 105.05}, "updated": "2026-05-27"}, "DBC": {"price": 29.49, "daily": -1.8, "returns": {"1M": -1.99, "3M": 19.15, "6M": 35.3, "1Y": 42.38, "3Y": 48.34}, "updated": "2026-05-27"}, "VNQ": {"price": 96.92, "daily": -0.31, "returns": {"1M": 2.26, "3M": 3.25, "6M": 10.36, "1Y": 15.71, "3Y": 36.09}, "updated": "2026-05-27"}, "ARKK": {"price": 77.95, "daily": 0.93, "returns": {"1M": 1.83, "3M": 6.0, "6M": 6.27, "1Y": 39.02, "3Y": 103.1}, "updated": "2026-05-27"}, "ARKG": {"price": 32.06, "daily": 2.43, "returns": {"1M": 7.19, "3M": 9.64, "6M": 10.48, "1Y": 53.25, "3Y": 4.23}, "updated": "2026-05-27"}, "ARKW": {"price": 146.16, "daily": 0.09, "returns": {"1M": 5.53, "3M": 15.0, "6M": 5.01, "1Y": 24.79, "3Y": 196.07}, "updated": "2026-05-27"}, "ARKF": {"price": 41.045, "daily": 0.6, "returns": {"1M": -3.26, "3M": 4.76, "6M": -10.26, "1Y": 1.23, "3Y": 119.57}, "updated": "2026-05-27"}, "ICLN": {"price": 23.15, "daily": 0.96, "returns": {"1M": 14.72, "3M": 21.27, "6M": 45.18, "1Y": 87.87, "3Y": 30.53}, "updated": "2026-05-27"}, "SOXX": {"price": 563.98, "daily": -1.07, "returns": {"1M": 23.84, "3M": 53.35, "6M": 108.67, "1Y": 180.21, "3Y": 290.19}, "updated": "2026-05-27"}, "SMH": {"price": 595.5, "daily": -1.1, "returns": {"1M": 17.63, "3M": 39.74, "6M": 83.16, "1Y": 151.58, "3Y": 352.83}, "updated": "2026-05-27"}, "IBB": {"price": 169.88, "daily": 0.27, "returns": {"1M": 0.51, "3M": -3.02, "6M": 1.59, "1Y": 40.44, "3Y": 31.68}, "updated": "2026-05-27"}, "XBI": {"price": 134.45, "daily": 0.82, "returns": {"1M": 1.06, "3M": 4.81, "6M": 15.64, "1Y": 70.73, "3Y": 58.34}, "updated": "2026-05-27"}, "JETS": {"price": 29.08, "daily": 2.9, "returns": {"1M": 13.91, "3M": 0.59, "6M": 19.62, "1Y": 33.75, "3Y": 58.91}, "updated": "2026-05-27"}, "BOTZ": {"price": 40.07, "daily": -2.03, "returns": {"1M": 4.1, "3M": 1.03, "6M": 20.16, "1Y": 31.97, "3Y": 52.29}, "updated": "2026-05-27"}, "VYM": {"price": 158.37, "daily": -0.2, "returns": {"1M": 2.44, "3M": 2.75, "6M": 14.46, "1Y": 27.78, "3Y": 66.39}, "updated": "2026-05-27"}, "SCHD": {"price": 32.55, "daily": -0.37, "returns": {"1M": 4.56, "3M": 4.17, "6M": 22.37, "1Y": 30.58, "3Y": 54.69}, "updated": "2026-05-27"}, "DVY": {"price": 155.28, "daily": 0.03, "returns": {"1M": 1.88, "3M": 0.2, "6M": 13.07, "1Y": 23.67, "3Y": 56.03}, "updated": "2026-05-27"}, "SDY": {"price": 150.03, "daily": -0.09, "returns": {"1M": 1.26, "3M": -2.34, "6M": 9.97, "1Y": 15.81, "3Y": 34.11}, "updated": "2026-05-27"}, "HDV": {"price": 27.58, "daily": -0.22, "returns": {"1M": 3.43, "3M": -0.0, "6M": 14.33, "1Y": 23.71, "3Y": 54.09}, "updated": "2026-05-27"}, "DGRO": {"price": 74.57, "daily": -0.05, "returns": {"1M": 2.73, "3M": 1.68, "6M": 10.77, "1Y": 24.52, "3Y": 59.73}, "updated": "2026-05-27"}, "TQQQ": {"price": 81.67, "daily": -0.34, "returns": {"1M": 30.38, "3M": 57.71, "6M": 72.56, "1Y": 148.01, "3Y": 432.91}, "updated": "2026-05-27"}, "SQQQ": {"price": 39.44, "daily": 0.41, "returns": {"1M": -24.8, "3M": -41.22, "6M": -48.65, "1Y": -66.75, "3Y": -92.42}, "updated": "2026-05-27"}, "UPRO": {"price": 145.84, "daily": -0.01, "returns": {"1M": 14.3, "3M": 22.88, "6M": 39.1, "1Y": 93.97, "3Y": 272.02}, "updated": "2026-05-27"}, "SPXU": {"price": 37.17, "daily": 0.03, "returns": {"1M": -12.95, "3M": -21.56, "6M": -31.91, "1Y": -52.55, "3Y": -82.39}, "updated": "2026-05-27"}, "_benchmark": "SPY", "_updated": "2026-05-27"}