{"SPY": {"price": 720.65, "daily": 0.28, "returns": {"1M": 9.98, "3M": 4.43, "6M": 5.44, "1Y": 31.44, "3Y": 85.2}, "updated": "2026-05-01"}, "IVV": {"price": 724.01, "daily": 0.27, "returns": {"1M": 10.02, "3M": 4.45, "6M": 5.47, "1Y": 31.37, "3Y": 85.66}, "updated": "2026-05-01"}, "VOO": {"price": 662.52, "daily": 0.29, "returns": {"1M": 10.0, "3M": 4.46, "6M": 5.47, "1Y": 31.53, "3Y": 85.7}, "updated": "2026-05-01"}, "VTI": {"price": 355.29, "daily": 0.31, "returns": {"1M": 9.92, "3M": 4.65, "6M": 5.83, "1Y": 31.77, "3Y": 84.27}, "updated": "2026-05-01"}, "ITOT": {"price": 157.76, "daily": 0.3, "returns": {"1M": 9.98, "3M": 4.73, "6M": 5.8, "1Y": 31.88, "3Y": 84.28}, "updated": "2026-05-01"}, "SCHB": {"price": 27.82, "daily": 0.32, "returns": {"1M": 9.96, "3M": 4.68, "6M": 5.76, "1Y": 31.84, "3Y": 84.36}, "updated": "2026-05-01"}, "IWM": {"price": 279.28, "daily": 0.47, "returns": {"1M": 11.91, "3M": 7.75, "6M": 13.72, "1Y": 44.87, "3Y": 68.88}, "updated": "2026-05-01"}, "IWF": {"price": 120.05, "daily": 0.65, "returns": {"1M": 11.65, "3M": 3.15, "6M": -2.16, "1Y": 31.42, "3Y": 103.05}, "updated": "2026-05-01"}, "IWD": {"price": 230.86, "daily": -0.17, "returns": {"1M": 7.41, "3M": 5.4, "6M": 13.74, "1Y": 28.89, "3Y": 62.38}, "updated": "2026-05-01"}, "MDY": {"price": 664.35, "daily": 0.03, "returns": {"1M": 6.84, "3M": 6.12, "6M": 12.21, "1Y": 29.1, "3Y": 55.44}, "updated": "2026-05-01"}, "IJH": {"price": 72.81, "daily": 0.05, "returns": {"1M": 6.92, "3M": 6.28, "6M": 12.43, "1Y": 29.7, "3Y": 56.79}, "updated": "2026-05-01"}, "IJR": {"price": 137.44, "daily": 0.25, "returns": {"1M": 10.02, "3M": 8.37, "6M": 16.32, "1Y": 39.14, "3Y": 57.25}, "updated": "2026-05-01"}, "QQQ": {"price": 674.15, "daily": 0.96, "returns": {"1M": 15.38, "3M": 8.54, "6M": 6.31, "1Y": 42.47, "3Y": 120.0}, "updated": "2026-05-01"}, "QQQM": {"price": 277.54, "daily": 0.96, "returns": {"1M": 15.37, "3M": 8.54, "6M": 6.3, "1Y": 42.47, "3Y": 120.54}, "updated": "2026-05-01"}, "VUG": {"price": 83.86, "daily": 0.83, "returns": {"1M": 13.95, "3M": 4.6, "6M": -0.01, "1Y": 33.59, "3Y": 109.2}, "updated": "2026-05-01"}, "VONG": {"price": 123.55, "daily": 0.64, "returns": {"1M": 11.62, "3M": 3.06, "6M": -2.1, "1Y": 31.7, "3Y": 103.7}, "updated": "2026-05-01"}, "IWY": {"price": 281.0, "daily": 0.73, "returns": {"1M": 11.95, "3M": 3.28, "6M": -2.35, "1Y": 31.7, "3Y": 108.12}, "updated": "2026-05-01"}, "VEA": {"price": 68.72, "daily": -0.12, "returns": {"1M": 5.5, "3M": 3.98, "6M": 14.18, "1Y": 34.1, "3Y": 65.52}, "updated": "2026-05-01"}, "VWO": {"price": 58.99, "daily": 0.1, "returns": {"1M": 8.82, "3M": 4.46, "6M": 7.85, "1Y": 34.0, "3Y": 64.26}, "updated": "2026-05-01"}, "EFA": {"price": 102.1, "daily": -0.22, "returns": {"1M": 3.54, "3M": 1.35, "6M": 9.28, "1Y": 24.78, "3Y": 54.6}, "updated": "2026-05-01"}, "EEM": {"price": 64.13, "daily": 0.22, "returns": {"1M": 12.06, "3M": 8.51, "6M": 16.14, "1Y": 50.09, "3Y": 79.79}, "updated": "2026-05-01"}, "IEFA": {"price": 95.39, "daily": -0.16, "returns": {"1M": 3.79, "3M": 1.42, "6M": 9.68, "1Y": 25.75, "3Y": 55.61}, "updated": "2026-05-01"}, "IEMG": {"price": 78.65, "daily": 0.2, "returns": {"1M": 11.91, "3M": 8.39, "6M": 15.73, "1Y": 49.52, "3Y": 80.39}, "updated": "2026-05-01"}, "VGK": {"price": 87.15, "daily": 0.01, "returns": {"1M": 4.22, "3M": 0.07, "6M": 9.06, "1Y": 23.33, "3Y": 53.55}, "updated": "2026-05-01"}, "EWJ": {"price": 88.3, "daily": -0.9, "returns": {"1M": 2.1, "3M": 3.01, "6M": 10.06, "1Y": 29.28, "3Y": 65.3}, "updated": "2026-05-01"}, "FXI": {"price": 36.81, "daily": 0.05, "returns": {"1M": 3.52, "3M": -7.07, "6M": -9.18, "1Y": 11.44, "3Y": 42.55}, "updated": "2026-05-01"}, "EWZ": {"price": 39.43, "daily": -0.68, "returns": {"1M": 2.76, "3M": 6.45, "6M": 30.89, "1Y": 53.74, "3Y": 73.74}, "updated": "2026-05-01"}, "AGG": {"price": 98.9, "daily": -0.2, "returns": {"1M": -0.1, "3M": -0.26, "6M": 0.07, "1Y": 3.88, "3Y": 10.66}, "updated": "2026-05-01"}, "BND": {"price": 73.36, "daily": -0.19, "returns": {"1M": -0.08, "3M": -0.2, "6M": 0.11, "1Y": 3.79, "3Y": 10.59}, "updated": "2026-05-01"}, "TLT": {"price": 85.61, "daily": -0.01, "returns": {"1M": -0.75, "3M": -0.65, "6M": -3.91, "1Y": 0.03, "3Y": -8.65}, "updated": "2026-05-01"}, "IEF": {"price": 94.74, "daily": -0.25, "returns": {"1M": -0.32, "3M": -0.31, "6M": -0.42, "1Y": 2.45, "3Y": 5.72}, "updated": "2026-05-01"}, "SHY": {"price": 82.25, "daily": -0.28, "returns": {"1M": -0.09, "3M": -0.03, "6M": 0.96, "1Y": 2.69, "3Y": 11.63}, "updated": "2026-05-01"}, "LQD": {"price": 108.6, "daily": -0.23, "returns": {"1M": -0.06, "3M": -0.67, "6M": -1.08, "1Y": 5.21, "3Y": 13.17}, "updated": "2026-05-01"}, "HYG": {"price": 80.06, "daily": -0.4, "returns": {"1M": 0.87, "3M": 0.15, "6M": 1.82, "1Y": 7.96, "3Y": 27.74}, "updated": "2026-05-01"}, "MUB": {"price": 106.81, "daily": -0.3, "returns": {"1M": 0.47, "3M": -0.18, "6M": 1.04, "1Y": 5.3, "3Y": 9.2}, "updated": "2026-05-01"}, "VCIT": {"price": 82.58, "daily": -0.33, "returns": {"1M": 0.07, "3M": -0.48, "6M": 0.17, "1Y": 5.86, "3Y": 17.36}, "updated": "2026-05-01"}, "XLK": {"price": 161.87, "daily": 1.49, "returns": {"1M": 19.98, "3M": 12.64, "6M": 6.74, "1Y": 55.07, "3Y": 126.21}, "updated": "2026-05-01"}, "XLF": {"price": 51.92, "daily": -0.4, "returns": {"1M": 5.02, "3M": -2.34, "6M": 0.54, "1Y": 8.12, "3Y": 68.93}, "updated": "2026-05-01"}, "XLV": {"price": 145.16, "daily": -0.57, "returns": {"1M": -1.74, "3M": -5.81, "6M": 1.67, "1Y": 5.18, "3Y": 15.86}, "updated": "2026-05-01"}, "XLE": {"price": 58.85, "daily": -1.34, "returns": {"1M": -0.2, "3M": 16.03, "6M": 35.76, "1Y": 50.91, "3Y": 55.37}, "updated": "2026-05-01"}, "XLY": {"price": 118.63, "daily": 0.24, "returns": {"1M": 8.04, "3M": -1.9, "6M": -0.39, "1Y": 21.23, "3Y": 69.21}, "updated": "2026-05-01"}, "XLP": {"price": 84.17, "daily": -0.17, "returns": {"1M": 3.33, "3M": 1.36, "6M": 11.42, "1Y": 5.7, "3Y": 19.89}, "updated": "2026-05-01"}, "XLI": {"price": 172.96, "daily": -0.93, "returns": {"1M": 5.19, "3M": 4.84, "6M": 12.23, "1Y": 33.59, "3Y": 86.24}, "updated": "2026-05-01"}, "XLB": {"price": 51.35, "daily": -0.23, "returns": {"1M": 1.76, "3M": 4.69, "6M": 18.72, "1Y": 24.82, "3Y": 38.67}, "updated": "2026-05-01"}, "XLU": {"price": 46.55, "daily": -0.64, "returns": {"1M": 0.95, "3M": 8.38, "6M": 4.83, "1Y": 21.36, "3Y": 49.51}, "updated": "2026-05-01"}, "XLRE": {"price": 44.32, "daily": -0.18, "returns": {"1M": 8.23, "3M": 7.69, "6M": 10.96, "1Y": 11.04, "3Y": 34.85}, "updated": "2026-05-01"}, "XLC": {"price": 116.72, "daily": 0.18, "returns": {"1M": 4.93, "3M": -2.49, "6M": 1.02, "1Y": 23.81, "3Y": 114.88}, "updated": "2026-05-01"}, "GLD": {"price": 423.18, "daily": -0.11, "returns": {"1M": -3.34, "3M": -4.89, "6M": 16.58, "1Y": 39.31, "3Y": 129.07}, "updated": "2026-05-01"}, "SLV": {"price": 68.29, "daily": 2.45, "returns": {"1M": 0.22, "3M": -9.48, "6M": 57.97, "1Y": 130.71, "3Y": 199.12}, "updated": "2026-05-01"}, "GDX": {"price": 87.11, "daily": -1.34, "returns": {"1M": -9.27, "3M": -7.53, "6M": 23.46, "1Y": 79.03, "3Y": 170.72}, "updated": "2026-05-01"}, "USO": {"price": 142.8, "daily": -2.92, "returns": {"1M": 15.08, "3M": 79.58, "6M": 98.89, "1Y": 124.67, "3Y": 118.48}, "updated": "2026-05-01"}, "DBC": {"price": 30.81, "daily": -0.93, "returns": {"1M": 7.43, "3M": 26.12, "6M": 40.23, "1Y": 54.82, "3Y": 50.99}, "updated": "2026-05-01"}, "VNQ": {"price": 96.06, "daily": -0.28, "returns": {"1M": 7.91, "3M": 6.92, "6M": 10.67, "1Y": 13.08, "3Y": 34.76}, "updated": "2026-05-01"}, "ARKK": {"price": 76.92, "daily": 1.42, "returns": {"1M": 12.46, "3M": 2.74, "6M": -13.8, "1Y": 51.3, "3Y": 120.22}, "updated": "2026-05-01"}, "ARKG": {"price": 30.3, "daily": 1.44, "returns": {"1M": 11.85, "3M": -0.43, "6M": 1.1, "1Y": 37.79, "3Y": 5.52}, "updated": "2026-05-01"}, "ARKW": {"price": 140.03, "daily": 2.22, "returns": {"1M": 15.46, "3M": 2.28, "6M": -20.49, "1Y": 38.17, "3Y": 204.42}, "updated": "2026-05-01"}, "ARKF": {"price": 42.04, "daily": 2.04, "returns": {"1M": 10.81, "3M": -2.89, "6M": -26.94, "1Y": 16.62, "3Y": 143.92}, "updated": "2026-05-01"}, "ICLN": {"price": 20.95, "daily": 0.87, "returns": {"1M": 14.79, "3M": 15.43, "6M": 21.9, "1Y": 81.29, "3Y": 18.25}, "updated": "2026-05-01"}, "SOXX": {"price": 465.75, "daily": 0.93, "returns": {"1M": 37.58, "3M": 34.58, "6M": 50.75, "1Y": 154.96, "3Y": 253.89}, "updated": "2026-05-01"}, "SMH": {"price": 509.82, "daily": 0.61, "returns": {"1M": 30.07, "3M": 26.36, "6M": 38.74, "1Y": 142.05, "3Y": 329.12}, "updated": "2026-05-01"}, "IBB": {"price": 167.27, "daily": -0.84, "returns": {"1M": -1.68, "3M": -2.92, "6M": 6.75, "1Y": 32.46, "3Y": 31.01}, "updated": "2026-05-01"}, "XBI": {"price": 130.42, "daily": -0.69, "returns": {"1M": 1.45, "3M": 4.55, "6M": 17.93, "1Y": 57.81, "3Y": 65.24}, "updated": "2026-05-01"}, "JETS": {"price": 25.76, "daily": 1.34, "returns": {"1M": 1.94, "3M": -7.84, "6M": 5.87, "1Y": 31.03, "3Y": 47.65}, "updated": "2026-05-01"}, "BOTZ": {"price": 38.6, "daily": 0.39, "returns": {"1M": 13.86, "3M": 3.43, "6M": 1.59, "1Y": 36.07, "3Y": 58.97}, "updated": "2026-05-01"}, "VYM": {"price": 156.51, "daily": -0.43, "returns": {"1M": 5.79, "3M": 4.98, "6M": 12.07, "1Y": 29.01, "3Y": 62.87}, "updated": "2026-05-01"}, "SCHD": {"price": 31.86, "daily": -0.65, "returns": {"1M": 4.42, "3M": 7.74, "6M": 21.38, "1Y": 28.16, "3Y": 50.35}, "updated": "2026-05-01"}, "DVY": {"price": 154.63, "daily": -0.53, "returns": {"1M": 2.38, "3M": 3.56, "6M": 12.23, "1Y": 25.01, "3Y": 50.42}, "updated": "2026-05-01"}, "SDY": {"price": 149.14, "daily": -0.62, "returns": {"1M": 2.26, "3M": 0.89, "6M": 10.23, "1Y": 16.88, "3Y": 32.47}, "updated": "2026-05-01"}, "HDV": {"price": 27.34, "daily": -0.47, "returns": {"1M": 2.04, "3M": 4.05, "6M": 16.1, "1Y": 22.63, "3Y": 49.58}, "updated": "2026-05-01"}, "DGRO": {"price": 73.43, "daily": -0.35, "returns": {"1M": 4.6, "3M": 2.71, "6M": 8.7, "1Y": 24.77, "3Y": 57.89}, "updated": "2026-05-01"}, "TQQQ": {"price": 65.3, "daily": 2.77, "returns": {"1M": 51.05, "3M": 21.13, "6M": 8.63, "1Y": 139.64, "3Y": 427.87}, "updated": "2026-05-01"}, "SQQQ": {"price": 50.22, "daily": -2.77, "returns": {"1M": -35.16, "3M": -23.59, "6M": -18.83, "1Y": -65.71, "3Y": -92.32}, "updated": "2026-05-01"}, "UPRO": {"price": 130.3, "daily": 0.87, "returns": {"1M": 31.39, "3M": 9.18, "6M": 8.32, "1Y": 95.0, "3Y": 264.26}, "updated": "2026-05-01"}, "SPXU": {"price": 41.81, "daily": -0.76, "returns": {"1M": -24.57, "3M": -12.08, "6M": -12.93, "1Y": -53.09, "3Y": -82.1}, "updated": "2026-05-01"}, "_benchmark": "SPY", "_updated": "2026-05-01"}